{
    "version":  "2.1.0",
    "title":  "QLTV 2.1.0",
    "release_date":  "2026-07-21",
    "download_url":  "https://github.com/Mentornoob/QLTV-Updates/releases/download/v2.1.0/QLTV_Setup_v2.1.0.exe",
    "sha256":  "a05c5e7036942d6d38d1b99f3804374e71684b1dec3cb3689e9d8caabb083906",
    "checksum_url":  "https://github.com/Mentornoob/QLTV-Updates/releases/download/v2.1.0/QLTV_Setup_v2.1.0.exe.sha256",
    "source_commit":  "76297b0c736194c0624524cd2d6deecc3266f98e",
    "notes":  [
                  "Nâng cấp toàn diện giao diện desktop, kích thước, bố cục và khả năng truy cập.",
                  "Thêm tra cứu nhanh danh mục, lọc tồn kho, xuất Excel và ghi nhớ bố cục.",
                  "Sửa lỗi mượn vượt tồn, đối soát lượt trả, cấu hình, báo cáo và cập nhật.",
                  "Bảo vệ dịch vụ MySQL của người dùng và giảm dung lượng bộ cài.",
                  "Gia cố pipeline phát hành với kiểm tra artifact và SHA-256."
              ]
}
